app_state-0.7.dist-info/METADATA
app_state-0.7.dist-info/WHEEL
app_state-0.7.dist-info/entry_points.txt
app_state.py
app_state-0.7.dist-info/RECORD
