Metadata-Version: 2.1
Name: app_state
Version: 0.7
Summary: app_state
Author-Email: Evstifeev Roman <someuniquename@gmail.com>, Roman Evstifeev <someuniquename@gmail.com>
License: MIT
Classifier: Development Status :: 4 - Beta
Classifier: Intended Audience :: Developers
Classifier: License :: OSI Approved :: MIT License
Classifier: Operating System :: Android
Classifier: Operating System :: MacOS :: MacOS X
Classifier: Operating System :: Microsoft :: Windows
Classifier: Operating System :: OS Independent
Classifier: Operating System :: POSIX :: Linux
Classifier: Programming Language :: Python :: 3
Classifier: Topic :: Software Development
Classifier: Topic :: Utilities
Project-URL: Homepage, https://github.com/Fak3/app_state
Requires-Python: >=3.11
Requires-Dist: lockorator
Requires-Dist: sniffio
Requires-Dist: getinstance>=0.7
